contrast_calculus/__init__.py
contrast_calculus/algebra.py
contrast_calculus/category.py
contrast_calculus/cocycle.py
contrast_calculus-1.0.3.dist-info/licenses/LICENSE
contrast_calculus-1.0.3.dist-info/METADATA
contrast_calculus-1.0.3.dist-info/WHEEL
contrast_calculus-1.0.3.dist-info/entry_points.txt
contrast_calculus-1.0.3.dist-info/top_level.txt
contrast_calculus-1.0.3.dist-info/RECORD
